[
     {
          "data": "100_0_1_w.mod",
          "objective": 17216522.92144631,
          "fitness": 0.010764701958395507,
          "gap_power_rate": 0.015724283824280656,
          "gap_price_rate": 0.005805120092510356,
          "solve_time": 0.02471017837524414
     },
     {
          "data": "100_0_2_w.mod",
          "objective": 16276359.620153893,
          "fitness": 0.001098668021589403,
          "gap_power_rate": 1.1214338496515334e-16,
          "gap_price_rate": 0.0021973360431786935,
          "solve_time": 0.022821903228759766
     },
     {
          "data": "100_0_3_w.mod",
          "objective": 16369909.502848057,
          "fitness": 0.0026299431149419366,
          "gap_power_rate": 1.5964957478379368e-16,
          "gap_price_rate": 0.005259886229883714,
          "solve_time": 0.022798538208007812
     },
     {
          "data": "100_0_4_w.mod",
          "objective": 15991571.9902154,
          "fitness": 0.0034196077119099675,
          "gap_power_rate": 1.751107248828164e-16,
          "gap_price_rate": 0.00683921542381976,
          "solve_time": 0.024914264678955078
     },
     {
          "data": "100_0_5_w.mod",
          "objective": 17354735.53220201,
          "fitness": 0.00335539160333372,
          "gap_power_rate": 0.0034021390296373544,
          "gap_price_rate": 0.0033086441770300854,
          "solve_time": 0.01963186264038086
     },
     {
          "data": "10_0_1_w.mod",
          "objective": 1951937.0617641006,
          "fitness": 0.004232539193210121,
          "gap_power_rate": 4.4184433732347295e-05,
          "gap_price_rate": 0.008420893952687894,
          "solve_time": 0.004099607467651367
     },
     {
          "data": "10_0_2_w.mod",
          "objective": 1400423.0767923917,
          "fitness": 0.001551047719808211,
          "gap_power_rate": 1.1093159355763246e-17,
          "gap_price_rate": 0.0031020954396164106,
          "solve_time": 0.002034425735473633
     },
     {
          "data": "10_0_3_w.mod",
          "objective": 1823641.3376680189,
          "fitness": 0.02065040294075636,
          "gap_power_rate": 0.025043860155853446,
          "gap_price_rate": 0.016256945725659274,
          "solve_time": 0.0030083656311035156
     },
     {
          "data": "10_0_4_w.mod",
          "objective": 1786082.0421553983,
          "fitness": 0.05281840780859645,
          "gap_power_rate": 0.04732325285292588,
          "gap_price_rate": 0.058313562764267024,
          "solve_time": 0.0020651817321777344
     },
     {
          "data": "10_std.mod",
          "objective": 574150.3363738998,
          "fitness": 0.007215489847853426,
          "gap_power_rate": 0.0029372693726937237,
          "gap_price_rate": 0.011493710323013127,
          "solve_time": 0.0030083656311035156
     },
     {
          "data": "150_0_1_w.mod",
          "objective": 27544501.348342955,
          "fitness": 0.011539005243602787,
          "gap_power_rate": 0.013895813382861086,
          "gap_price_rate": 0.009182197104344487,
          "solve_time": 0.03530406951904297
     },
     {
          "data": "150_0_2_w.mod",
          "objective": 25707029.881633304,
          "fitness": 0.004542624624601905,
          "gap_power_rate": 0.004703532628169799,
          "gap_price_rate": 0.004381716621034012,
          "solve_time": 0.04452943801879883
     },
     {
          "data": "150_0_3_w.mod",
          "objective": 25877570.503107566,
          "fitness": 0.0035970801648956938,
          "gap_power_rate": 0.001294440827216303,
          "gap_price_rate": 0.005899719502575084,
          "solve_time": 0.04247570037841797
     },
     {
          "data": "150_0_4_w.mod",
          "objective": 23150000.174043007,
          "fitness": 0.0006144248229464132,
          "gap_power_rate": 1.35354817935463e-16,
          "gap_price_rate": 0.001228849645892691,
          "solve_time": 0.03436923027038574
     },
     {
          "data": "150_0_5_w.mod",
          "objective": 24388411.421611637,
          "fitness": 0.0019568466133609913,
          "gap_power_rate": 0.0009149079413341246,
          "gap_price_rate": 0.0029987852853878578,
          "solve_time": 0.04477834701538086
     },
     {
          "data": "200_0_10_w.mod",
          "objective": 38924589.72622206,
          "fitness": 0.003506081141376348,
          "gap_power_rate": 0.006248451815208198,
          "gap_price_rate": 0.0007637104675444981,
          "solve_time": 0.046391963958740234
     },
     {
          "data": "200_0_11_w.mod",
          "objective": 35467368.866397806,
          "fitness": 0.0066359024633225495,
          "gap_power_rate": 1.6837310196861498e-16,
          "gap_price_rate": 0.01327180492664493,
          "solve_time": 0.05431628227233887
     },
     {
          "data": "200_0_12_w.mod",
          "objective": 33679147.317998126,
          "fitness": 0.00583696817097205,
          "gap_power_rate": 1.7216668685458103e-16,
          "gap_price_rate": 0.011673936341943929,
          "solve_time": 0.04438972473144531
     },
     {
          "data": "200_0_1_w.mod",
          "objective": 35695019.974439844,
          "fitness": 0.007111010570012748,
          "gap_power_rate": 0.009374755428070512,
          "gap_price_rate": 0.004847265711954985,
          "solve_time": 0.0350949764251709
     },
     {
          "data": "200_0_2_w.mod",
          "objective": 33071645.868938398,
          "fitness": 0.002884068755477054,
          "gap_power_rate": 0.0030147601471268133,
          "gap_price_rate": 0.0027533773638272942,
          "solve_time": 0.06383395195007324
     },
     {
          "data": "200_0_3_w.mod",
          "objective": 31480759.51468977,
          "fitness": 0.000910956842893604,
          "gap_power_rate": 0.0012090956906997206,
          "gap_price_rate": 0.0006128179950874872,
          "solve_time": 0.04949498176574707
     },
     {
          "data": "200_0_4_w.mod",
          "objective": 31170685.454340477,
          "fitness": 0.004794496401821848,
          "gap_power_rate": 0.0008587263825794438,
          "gap_price_rate": 0.008730266421064252,
          "solve_time": 0.046172380447387695
     },
     {
          "data": "200_0_5_w.mod",
          "objective": 34516656.179931305,
          "fitness": 0.004461395862032714,
          "gap_power_rate": 0.003395668762562271,
          "gap_price_rate": 0.005527122961503157,
          "solve_time": 0.054378509521484375
     },
     {
          "data": "200_0_6_w.mod",
          "objective": 31821242.70939654,
          "fitness": 0.005786980864466342,
          "gap_power_rate": 1.6380876167019933e-16,
          "gap_price_rate": 0.011573961728932521,
          "solve_time": 0.03772401809692383
     },
     {
          "data": "200_0_7_w.mod",
          "objective": 37803026.35338881,
          "fitness": 0.0027484052151437468,
          "gap_power_rate": 0.003977121613573144,
          "gap_price_rate": 0.00151968881671435,
          "solve_time": 0.052815914154052734
     },
     {
          "data": "200_0_8_w.mod",
          "objective": 35011509.12604485,
          "fitness": 0.0050608356171870685,
          "gap_power_rate": 1.4893995945092416e-16,
          "gap_price_rate": 0.010121671234373988,
          "solve_time": 0.047651052474975586
     },
     {
          "data": "200_0_9_w.mod",
          "objective": 37480107.67281826,
          "fitness": 0.003458975956748699,
          "gap_power_rate": 0.0015930560345661076,
          "gap_price_rate": 0.00532489587893129,
          "solve_time": 0.06228208541870117
     },
     {
          "data": "20_0_1_w.mod",
          "objective": 3026246.1749275946,
          "fitness": 0.006134341192415085,
          "gap_power_rate": 2.950003076944962e-17,
          "gap_price_rate": 0.012268682384830141,
          "solve_time": 0.003000974655151367
     },
     {
          "data": "20_0_2_w.mod",
          "objective": 3729591.35262895,
          "fitness": 0.059576448462686546,
          "gap_power_rate": 0.060850112582283726,
          "gap_price_rate": 0.05830278434308936,
          "solve_time": 0.006359100341796875
     },
     {
          "data": "20_0_3_w.mod",
          "objective": 3047279.691137615,
          "fitness": 0.004820564236605267,
          "gap_power_rate": 6.007254039045433e-17,
          "gap_price_rate": 0.009641128473210473,
          "solve_time": 0.005000591278076172
     },
     {
          "data": "20_0_4_w.mod",
          "objective": 2633637.492860684,
          "fitness": 0.02425534077521222,
          "gap_power_rate": 7.895327450081142e-17,
          "gap_price_rate": 0.048510681550424366,
          "solve_time": 0.00630640983581543
     },
     {
          "data": "20_0_5_w.mod",
          "objective": 3783100.765716337,
          "fitness": 0.007127822613028847,
          "gap_power_rate": 0.006072238982760889,
          "gap_price_rate": 0.008183406243296805,
          "solve_time": 0.006001472473144531
     },
     {
          "data": "50_0_1_w.mod",
          "objective": 8629738.652635386,
          "fitness": 0.0038515096321544567,
          "gap_power_rate": 0.00017542095363600856,
          "gap_price_rate": 0.007527598310672905,
          "solve_time": 0.014003753662109375
     },
     {
          "data": "50_0_2_w.mod",
          "objective": 8694943.618310692,
          "fitness": 0.004375972590042328,
          "gap_power_rate": 0.002323860822335994,
          "gap_price_rate": 0.006428084357748661,
          "solve_time": 0.011829376220703125
     },
     {
          "data": "50_0_3_w.mod",
          "objective": 9049669.819961911,
          "fitness": 0.008761480659849752,
          "gap_power_rate": 0.008026349070435992,
          "gap_price_rate": 0.00949661224926351,
          "solve_time": 0.011002063751220703
     },
     {
          "data": "50_0_4_w.mod",
          "objective": 8538005.398187509,
          "fitness": 0.005210085148447587,
          "gap_power_rate": 9.404012402577081e-17,
          "gap_price_rate": 0.010420170296895081,
          "solve_time": 0.010017633438110352
     },
     {
          "data": "50_0_5_w.mod",
          "objective": 9906724.554778557,
          "fitness": 0.009235829297089427,
          "gap_power_rate": 0.012840649845434924,
          "gap_price_rate": 0.005631008748743929,
          "solve_time": 0.015004396438598633
     },
     {
          "data": "75_0_1_w.mod",
          "objective": 10176490.67120099,
          "fitness": 0.0058426813897221345,
          "gap_power_rate": 1.256465839057638e-16,
          "gap_price_rate": 0.011685362779444144,
          "solve_time": 0.012924909591674805
     },
     {
          "data": "75_0_2_w.mod",
          "objective": 12548318.601551516,
          "fitness": 0.0012695371811760948,
          "gap_power_rate": 0.00036866325836286217,
          "gap_price_rate": 0.0021704111039893273,
          "solve_time": 0.012003898620605469
     },
     {
          "data": "75_0_3_w.mod",
          "objective": 13192787.690635372,
          "fitness": 0.000857531849016293,
          "gap_power_rate": 0.0010781445049836567,
          "gap_price_rate": 0.0006369191930489293,
          "solve_time": 0.01795792579650879
     },
     {
          "data": "75_0_4_w.mod",
          "objective": 13322518.192593547,
          "fitness": 0.009806285785513066,
          "gap_power_rate": 0.010587245164970765,
          "gap_price_rate": 0.009025326406055368,
          "solve_time": 0.019893646240234375
     },
     {
          "data": "75_0_5_w.mod",
          "objective": 12409298.095348924,
          "fitness": 0.006302382527567395,
          "gap_power_rate": 1.2344449495166092e-16,
          "gap_price_rate": 0.012604765055134666,
          "solve_time": 0.015958309173583984
     }
]